nose2_test_timer/__init__.py
nose2_test_timer/plugin.py
nose2timer/__init__.py
nose2timer/plugin.py
nose2_test_timer-0.0.3.dist-info/METADATA
nose2_test_timer-0.0.3.dist-info/WHEEL
nose2_test_timer-0.0.3.dist-info/entry_points.txt
nose2_test_timer-0.0.3.dist-info/top_level.txt
nose2_test_timer-0.0.3.dist-info/RECORD
