Metadata-Version: 2.1
Name: nose2-test-timer
Version: 0.0.3
Summary: A timer plugin for nose2
Home-page: https://github.com/kaichiachen/nose2-test-timer
Author: Kaichia Chen
Author-email: kaichiaboy@gmail.com
License: MIT
Platform: UNKNOWN
Classifier: Intended Audience :: Developers
Classifier: License :: OSI Approved :: MIT License
Classifier: Natural Language :: English
Classifier: Operating System :: OS Independent
Classifier: Programming Language :: Python
Classifier: Programming Language :: Python :: 3.6
Classifier: Programming Language :: Python :: 3.7
Classifier: Programming Language :: Python :: Implementation :: CPython
Classifier: Programming Language :: Python :: Implementation :: PyPy
Classifier: Topic :: Software Development :: Testing
Classifier: Environment :: Console
Requires-Dist: nose2
Requires-Dist: colorama
